lhbtool1/__init__.py
lhbtool1/module.py
lhbtool1-1.0.1.dist-info/licenses/LICENSE
lhbtool1-1.0.1.dist-info/METADATA
lhbtool1-1.0.1.dist-info/WHEEL
lhbtool1-1.0.1.dist-info/top_level.txt
lhbtool1-1.0.1.dist-info/RECORD
