Metadata-Version: 2.4
Name: lhbtool1
Version: 1.0.1
Summary: 这是我的第一个 Python 包
Author: lvhongbin
License: MIT License
Requires-Python: >=3.6
License-File: LICENSE
Dynamic: license-file
